ensae_projects/__init__.py
ensae_projects/__main__.py
ensae_projects/rss_ensae_projects.xml
ensae_projects/automation/__init__.py
ensae_projects/automation/credentials_helper.py
ensae_projects/automation/notebook_test_helper.py
ensae_projects/challenge/__init__.py
ensae_projects/challenge/blossom.py
ensae_projects/challenge/city_tour.py
ensae_projects/challenge/velib_trajectories.py
ensae_projects/cli/__init__.py
ensae_projects/cli/img_helper.py
ensae_projects/datainc/__init__.py
ensae_projects/datainc/croix_rouge.py
ensae_projects/datainc/data_bikes.py
ensae_projects/datainc/data_cresus.py
ensae_projects/datainc/data_exception.py
ensae_projects/datainc/data_geo_streets.py
ensae_projects/datainc/data_helper.py
ensae_projects/datainc/data_medical.py
ensae_projects/datainc/datazips.py
ensae_projects/datainc/hackathon_2015_croix_rouge/ITMMASTER.schema.enc
ensae_projects/datainc/hackathon_2015_croix_rouge/SINVOICE.schema.enc
ensae_projects/datainc/hackathon_2015_croix_rouge/SINVOICE_V.schema.enc
ensae_projects/datainc/hackathon_2015_croix_rouge/__init__.py
ensae_projects/datainc/hackathon_2015_croix_rouge/meaning_invoice.enc
ensae_projects/datainc/hackathon_2015_croix_rouge/stojou.schema.enc
ensae_projects/datainc/hackathon_2016_cresus/__init__.py
ensae_projects/datainc/search_images/__init__.py
ensae_projects/datainc/search_images/cat-1192026__480.jpg
ensae_projects/datainc/seattle_streets/__init__.py
ensae_projects/datainc/seattle_streets/street_seattle.desc.xlsx
ensae_projects/datainc/zips/__init__.py
ensae_projects/datainc/zips/added.zip
ensae_projects/datainc/zips/besancon.df.txt.zip
ensae_projects/hackathon/__init__.py
ensae_projects/hackathon/crypt_helper.py
ensae_projects/hackathon/empty.jpg
ensae_projects/hackathon/image_helper.py
ensae_projects/hackathon/image_knn.py
ensae_projects/hackathon/json_helper.py
ensae_projects/hackathon/perf2018.py
ensae_projects/hackathon/web_search_helper.py
ensae_projects/ml/__init__.py
ensae_projects/ml/competitions.py
ensae_projects-0.3.619.dist-info/LICENSE.txt
ensae_projects-0.3.619.dist-info/METADATA
ensae_projects-0.3.619.dist-info/WHEEL
ensae_projects-0.3.619.dist-info/top_level.txt
ensae_projects-0.3.619.dist-info/RECORD
