Metadata-Version: 2.1
Name: ensae-projects
Version: 0.3.619
Summary: Helpers for projects, teachings, events.
Home-page: http://www.xavierdupre.fr/app/ensae_projects/helpsphinx/index.html
Author: Xavier Dupré
Author-email: xavier.dupre@gmail.com
License: MIT
Download-URL: https://github.com/sdpython/ensae_projects/
Keywords: ensae_projects,ENSAE,hackathon
Platform: UNKNOWN
Classifier: Programming Language :: Python :: 3
Classifier: Intended Audience :: Developers
Classifier: Topic :: Scientific/Engineering
Classifier: Topic :: Education
Classifier: License :: OSI Approved :: MIT License
Classifier: Development Status :: 5 - Production/Stable
Requires-Dist: pyquickhelper (>=1.9)
Requires-Dist: pyensae
Requires-Dist: pymyinstall
Requires-Dist: scikit-learn
Requires-Dist: pyrsslocal
Requires-Dist: pandas
Requires-Dist: numpy
Requires-Dist: matplotlib
Requires-Dist: jupyter
Requires-Dist: manydataapi
Requires-Dist: mlinsights
